BSE_optionChain.py
bse_options-0.1.1.dist-info/METADATA
bse_options-0.1.1.dist-info/WHEEL
bse_options-0.1.1.dist-info/top_level.txt
bse_options-0.1.1.dist-info/RECORD
