Metadata-Version: 2.4
Name: bse-options
Version: 0.1.1
Summary: Unofficial Python API for fetching BSE India Option Chain data
Author-email: Rishav Raj Bhagat <rishav.raj@rmoneyindia.com>
Project-URL: Homepage, http://192.168.100.117/quant/bse_option_chain
Project-URL: Source Code, http://192.168.100.117/quant/bse_option_chain
Requires-Python: >=3.12
Requires-Dist: mthrottle>=0.0.2
Requires-Dist: pandas>=2.3.3
Requires-Dist: requests>=2.32.5
